<?xml version="1.0"?>
<clickhouse>
    <profiles>
        <default>
            <max_memory_usage>4294967296</max_memory_usage>
            <max_bytes_before_external_sort>2147483648</max_bytes_before_external_sort>
            <max_bytes_before_external_group_by>2147483648</max_bytes_before_external_group_by>
            <max_threads>8</max_threads>
            <kafka_num_consumers>4</kafka_num_consumers>
            <allow_ddl>1</allow_ddl>
            <allow_experimental_object_type>1</allow_experimental_object_type>
            <output_format_pretty_max_rows>50000</output_format_pretty_max_rows>
            <readonly>0</readonly>
        </default>
        <readonly>
            <readonly>1</readonly>
            <max_memory_usage>2147483648</max_memory_usage>
            <max_threads>4</max_threads>
        </readonly>
    </profiles>
    <users>
        <default>
            <password></password>
            <networks>
                <ip>::/0</ip>
            </networks>
            <profile>default</profile>
            <quota>default</quota>
            <access_management>1</access_management>
            <named_collection_control>1</named_collection_control>
            <show_named_collections>1</show_named_collections>
            <show_named_collections_secrets>0</show_named_collections_secrets>
        </default>
        <clickhouse_client>
            <password></password>
            <networks>
                <ip>::/0</ip>
            </networks>
            <profile>default</profile>
            <quota>default</quota>
            <access_management>0</access_management>
        </clickhouse_client>
    </users>
    <quotas>
        <default>
            <interval>
                <duration>3600</duration>
                <queries>0</queries>
                <query_selects>0</query_selects>
                <query_inserts>0</query_inserts>
                <errors>0</errors>
                <result_rows>0</result_rows>
                <read_rows>0</read_rows>
                <execution_time>0</execution_time>
            </interval>
        </default>
    </quotas>
</clickhouse>
